meercat_libraries/flashx.py
meercat_libraries-1.3.dist-info/METADATA
meercat_libraries-1.3.dist-info/WHEEL
meercat_libraries-1.3.dist-info/top_level.txt
meercat_libraries-1.3.dist-info/RECORD
