Metadata-Version: 2.1
Name: meercat_libraries
Version: 1.3
Summary: for meeercat
Author: Stephen Fickas
Author-email: stephenfickas@gmail.com
Classifier: Programming Language :: Python :: 3
Classifier: License :: OSI Approved :: MIT License
Classifier: Operating System :: OS Independent
Requires-Python: >=3.6
